aiq/plugins/s3/__init__.py
aiq/plugins/s3/object_store.py
aiq/plugins/s3/register.py
aiq/plugins/s3/s3_object_store.py
aiqtoolkit_s3-1.2.0a20250806.dist-info/METADATA
aiqtoolkit_s3-1.2.0a20250806.dist-info/WHEEL
aiqtoolkit_s3-1.2.0a20250806.dist-info/entry_points.txt
aiqtoolkit_s3-1.2.0a20250806.dist-info/top_level.txt
aiqtoolkit_s3-1.2.0a20250806.dist-info/RECORD
